<?xml version="1.0" encoding="UTF-8" standalone="no"?><Packets><Packet id="FAILURE" type="0"/><Packet id="PING" type="1"/><Packet id="REQUESTTRADE" type="4"/><Packet id="PIC" type="5"/><Packet id="INVSWAP" type="6"/><Packet id="SETCONDITION" type="7"/><Packet id="CLIENTSTAT" type="8"/><Packet id="PONG" type="9"/><Packet id="SHOOT" type="10"/><Packet id="SHOOTACK" type="11"/><Packet id="CHANGETRADE" type="12"/><Packet id="TRADEDONE" type="13"/><Packet id="GOTO" type="14"/><Packet id="RECONNECT" type="15"/><Packet id="BUYRESULT" type="16"/><Packet id="LOAD" type="17"/><Packet id="GUILDREMOVE" type="19"/><Packet id="TEXT" type="20"/><Packet id="DAMAGE" type="21"/><Packet id="NAMERESULT" type="22"/><Packet id="CREATEGUILD" type="23"/><Packet id="AOE" type="24"/><Packet id="CANCELTRADE" type="25"/><Packet id="PLAYERHIT" type="26"/><Packet id="JOINGUILD" type="27"/><Packet id="EDITACCOUNTLIST" type="31"/><Packet id="CHECKCREDITS" type="33"/><Packet id="DEATH" type="34"/><Packet id="USEITEM" type="35"/><Packet id="CHANGEGUILDRANK" type="36"/><Packet id="AOEACK" type="37"/><Packet id="INVDROP" type="38"/><Packet id="GUILDINVITE" type="39"/><Packet id="BUY" type="40"/><Packet id="SQUAREHIT" type="41"/><Packet id="UPDATEACK" type="42"/><Packet id="GLOBAL_NOTIFICATION" type="45"/><Packet id="CREATE_SUCCESS" type="47"/><Packet id="QUESTOBJID" type="48"/><Packet id="CREATE" type="49"/><Packet id="NEW_TICK" type="50"/><Packet id="HELLO" type="51"/><Packet id="GROUNDDAMAGE" type="52"/><Packet id="INVRESULT" type="53"/><Packet id="USEPORTAL" type="55"/><Packet id="RESKIN" type="56"/><Packet id="CHOOSENAME" type="57"/><Packet id="ENEMYHIT" type="58"/><Packet id="SHOOT2" type="59"/><Packet id="PLAYSOUND" type="60"/><Packet id="GOTOACK" type="61"/><Packet id="ACCEPTTRADE" type="63"/><Packet id="TRADECHANGED" type="65"/><Packet id="UPDATE" type="66"/><Packet id="TELEPORT" type="67"/><Packet id="ESCAPE" type="69"/><Packet id="MOVE" type="74"/><Packet id="MAPINFO" type="76"/><Packet id="TRADESTART" type="77"/><Packet id="TRADEREQUESTED" type="78"/><Packet id="PLAYERTEXT" type="80"/><Packet id="ACCOUNTLIST" type="81"/><Packet id="SHOW_EFFECT" type="83"/><Packet id="INVITEDTOGUILD" type="85"/><Packet id="TRADEACCEPTED" type="86"/><Packet id="OTHERHIT" type="89"/><Packet id="PLAYERSHOOT" type="90"/><Packet id="NOTIFICATION" type="91"/><Packet id="ALLYSHOOT" type="92"/></Packets>